[
  {
    "id": "scorching_whip",
    "classId": "exo",
    "name": "Scorching Whip",
    "kind": "active",
    "description": "Cast a scorching solar flare that whips forward dealing fire damage to monsters hit.",
    "damageType": "fire",
    "tags": ["Cast", "Active", "Spell", "Melee"],
    "movementDuringUse": 85,
    "range": 320,
    "maxRank": 20,
    "requiresLevel": 1,
    "tree": "Solar Prophet",
    "position": { "row": 0, "col": 1 },
    "ranks": [{ "rank": 1, "manaCost": 5 }],
    "attackKind": "attack",
    "damageFormula": { "base": 5.2, "perLevel": 13.53 },
    "manaCostFormula": { "base": 5, "perLevel": 1.125 },
    "bonusSources": [
      { "source": "Whiplash", "stat": "fire_skill_damage", "value": 15, "per": "skill_level" },
      { "source": "Solar Dash", "stat": "fire_skill_damage", "value": 12.5, "per": "skill_level" },
      { "source": "Shine Bright", "stat": "fire_skill_damage", "value": 10, "per": "skill_level" },
      { "source": "Intelligence", "stat": "fire_skill_damage", "value": 8.25, "per": "attribute_point" }
    ]
  },
  {
    "id": "solar_flare",
    "classId": "exo",
    "name": "Solar Flare",
    "kind": "active",
    "description": "Unleash solar flare projectiles that homes towards monsters.",
    "damageType": "fire",
    "tags": ["Cast", "Active", "Spell", "Projectile", "Explosion"],
    "movementDuringUse": 65,
    "range": 320,
    "baseCastRate": 1,
    "maxRank": 20,
    "requiresLevel": 1,
    "tree": "Solar Prophet",
    "position": { "row": 0, "col": 2 },
    "ranks": [{ "rank": 1, "manaCost": 5 }],
    "damageFormula": { "base": 7.84, "perLevel": 9.16 },
    "manaCostFormula": { "base": 5, "perLevel": 1.075 },
    "bonusSources": [
      { "source": "Solar Burst", "stat": "fire_skill_damage", "value": 15, "per": "skill_level" },
      { "source": "Solar Form", "stat": "fire_skill_damage", "value": 10, "per": "skill_level" },
      { "source": "Blinding Light", "stat": "fire_skill_damage", "value": 12.5, "per": "skill_level" },
      { "source": "Intelligence", "stat": "fire_skill_damage", "value": 8, "per": "attribute_point" }
    ]
  },
  {
    "id": "whiplash",
    "classId": "exo",
    "name": "Whiplash",
    "kind": "passive",
    "description": "Scorching Whip now creates a chaining fire ball that bounces between monsters. Fire balls can hit the same target multiple times.",
    "tags": ["Passive", "Chaining"],
    "maxRank": 20,
    "requiresLevel": 8,
    "tree": "Solar Prophet",
    "position": { "row": 1, "col": 0 },
    "ranks": [{ "rank": 1 }],
    "passiveStats": {
      "base": { "of_total_damage": 20, "projectile_bounces": 6 },
      "perRank": { "of_total_damage": 2.25, "projectile_bounces": 0.1 }
    }
  },
  {
    "id": "solar_dash",
    "classId": "exo",
    "name": "Solar Dash",
    "kind": "active",
    "description": "Turn into a burning ball of fire traveling towards target location dealing fire damage leaving a trail of flames behind you.",
    "damageType": "fire",
    "tags": ["Cast", "Active", "Spell", "Movement", "Charge"],
    "movementDuringUse": 0,
    "baseCastRate": 1,
    "maxRank": 20,
    "requiresLevel": 8,
    "tree": "Solar Prophet",
    "position": { "row": 1, "col": 2 },
    "ranks": [{ "rank": 1, "manaCost": 5 }],
    "damageFormula": { "base": 0.63, "perLevel": 8.37 },
    "manaCostFormula": { "base": 5, "perLevel": 1.125 },
    "bonusSources": [
      { "source": "Solar Flare", "stat": "fire_skill_damage", "value": 15, "per": "skill_level" },
      { "source": "Blinding Light", "stat": "fire_skill_damage", "value": 12.5, "per": "skill_level" },
      { "source": "Solar Form", "stat": "fire_skill_damage", "value": 10, "per": "skill_level" },
      { "source": "Intelligence", "stat": "fire_skill_damage", "value": 9, "per": "attribute_point" }
    ]
  },
  {
    "id": "shine_bright",
    "classId": "exo",
    "name": "Shine Bright",
    "kind": "passive",
    "description": "Gain increased movement speed and attack speed.",
    "tags": ["Passive"],
    "maxRank": 20,
    "requiresLevel": 16,
    "tree": "Solar Prophet",
    "position": { "row": 2, "col": 0 },
    "ranks": [{ "rank": 1 }],
    "passiveStats": {
      "base": { "movement_speed": 0.75, "increased_attack_speed": 1 },
      "perRank": { "movement_speed": 0.75, "increased_attack_speed": 1 }
    }
  },
  {
    "id": "solar_form",
    "classId": "exo",
    "name": "Solar Form",
    "kind": "buff",
    "description": "Turn into a living sun and gain additional fire damage. Every time you cast an active ability in solar form you unleash a fiery pulse around you.",
    "damageType": "fire",
    "tags": ["Cast", "Active", "Buff", "Area of Effect", "Shape Shift"],
    "movementDuringUse": 85,
    "baseCastRate": 1,
    "baseCooldown": 70,
    "effectDuration": 25,
    "maxRank": 20,
    "requiresLevel": 16,
    "tree": "Solar Prophet",
    "position": { "row": 2, "col": 1 },
    "ranks": [{ "rank": 1, "manaCost": 10 }],
    "damageFormula": { "base": 0.3, "perLevel": 13.5 },
    "manaCostFormula": { "base": 10, "perLevel": 1.075 },
    "passiveStats": {
      "base": { "fire_skill_damage": 4 },
      "perRank": { "fire_skill_damage": 4 }
    },
    "bonusSources": [
      { "source": "Solar Flare", "stat": "fire_skill_damage", "value": 15, "per": "skill_level" },
      { "source": "Solar Dash", "stat": "fire_skill_damage", "value": 12.5, "per": "skill_level" },
      { "source": "Solar Burst", "stat": "fire_skill_damage", "value": 10, "per": "skill_level" },
      { "source": "Intelligence", "stat": "fire_skill_damage", "value": 7.35, "per": "attribute_point" }
    ]
  },
  {
    "id": "blinding_light",
    "classId": "exo",
    "name": "Blinding Light",
    "kind": "passive",
    "description": "You emit a blinding light that gives you chance to evade monster attacks. You also have increased cast rate while in Solar Form.",
    "tags": ["Passive"],
    "maxRank": 20,
    "requiresLevel": 24,
    "tree": "Solar Prophet",
    "position": { "row": 3, "col": 0 },
    "ranks": [{ "rank": 1 }],
    "passiveStats": {
      "base": { "dodge_chance": 1, "faster_cast_rate": 1 },
      "perRank": { "dodge_chance": 1, "faster_cast_rate": 1 }
    }
  },
  {
    "id": "solar_burst",
    "classId": "exo",
    "name": "Solar Burst",
    "kind": "passive",
    "description": "When you kill a monster, summon a burning burst of solar fire beneath the dead monster that deals area of effect fire damage.",
    "damageType": "fire",
    "tags": ["Active", "Spell", "Area of Effect"],
    "maxRank": 20,
    "requiresLevel": 24,
    "tree": "Solar Prophet",
    "position": { "row": 3, "col": 1 },
    "ranks": [{ "rank": 1 }],
    "damageFormula": { "base": 0, "perLevel": 22 },
    "proc": { "chance": 100, "trigger": "on_kill", "target": "Solar Burst" },
    "bonusSources": [
      { "source": "Solar Form", "stat": "fire_skill_damage", "value": 15, "per": "skill_level" },
      { "source": "Whiplash", "stat": "fire_skill_damage", "value": 12.5, "per": "skill_level" },
      { "source": "Supernova", "stat": "fire_skill_damage", "value": 10, "per": "skill_level" },
      { "source": "Intelligence", "stat": "fire_skill_damage", "value": 7.15, "per": "attribute_point" }
    ]
  },
  {
    "id": "supernova",
    "classId": "exo",
    "name": "Supernova",
    "kind": "active",
    "description": "Explode into a supernova dealing fire damage on a large radius.",
    "damageType": "fire",
    "tags": ["Cast", "Active", "Spell", "Area of Effect"],
    "movementDuringUse": 85,
    "baseCastRate": 1,
    "baseCooldown": 10,
    "maxRank": 20,
    "requiresLevel": 30,
    "tree": "Solar Prophet",
    "position": { "row": 4, "col": 1 },
    "ranks": [{ "rank": 1, "manaCost": 13 }],
    "damageFormula": { "base": 0.11, "perLevel": 23.89 },
    "manaCostFormula": { "base": 13, "perLevel": 1.125 },
    "bonusSources": [
      { "source": "Solar Flare", "stat": "fire_skill_damage", "value": 12.5, "per": "skill_level" },
      { "source": "Solar Dash", "stat": "fire_skill_damage", "value": 15, "per": "skill_level" },
      { "source": "Solar Burst", "stat": "fire_skill_damage", "value": 10, "per": "skill_level" },
      { "source": "Intelligence", "stat": "fire_skill_damage", "value": 7.25, "per": "attribute_point" }
    ]
  },
  {
    "id": "collision",
    "classId": "exo",
    "name": "Collision",
    "kind": "active",
    "description": "Leap forward from your orbit and smash the ground dealing cold damage in an area. Then dash forward on the surface of earth for short period of time and deal cold damage.",
    "damageType": "cold",
    "tags": ["Cast", "Active", "Spell", "Area of Effect"],
    "movementDuringUse": 0,
    "baseCastRate": 1,
    "maxRank": 20,
    "requiresLevel": 1,
    "tree": "Lunar Prophet",
    "position": { "row": 0, "col": 0 },
    "ranks": [{ "rank": 1, "manaCost": 5 }],
    "damageFormula": { "base": 0.8, "perLevel": 10.18 },
    "manaCostFormula": { "base": 5, "perLevel": 1.125 },
    "bonusSources": [
      { "source": "Lunar Form", "stat": "cold_skill_damage", "value": 12.5, "per": "skill_level" },
      { "source": "Asteroid", "stat": "cold_skill_damage", "value": 15, "per": "skill_level" },
      { "source": "Lunar Orbit", "stat": "cold_skill_damage", "value": 10, "per": "skill_level" },
      { "source": "Intelligence", "stat": "cold_skill_damage", "value": 7.35, "per": "attribute_point" }
    ]
  },
  {
    "id": "tsunami",
    "classId": "exo",
    "name": "Tsunami",
    "kind": "active",
    "description": "Direct your lunar mass to cast a wave of tsunami forward dealing cold damage.",
    "damageType": "cold",
    "tags": ["Cast", "Active", "Spell", "Projectile", "Area of Effect"],
    "movementDuringUse": 65,
    "range": 320,
    "baseCastRate": 1,
    "maxRank": 20,
    "requiresLevel": 1,
    "tree": "Lunar Prophet",
    "position": { "row": 0, "col": 2 },
    "ranks": [{ "rank": 1, "manaCost": 5 }],
    "damageFormula": { "base": 6, "perLevel": 13 },
    "manaCostFormula": { "base": 5, "perLevel": 1.125 },
    "bonusSources": [
      { "source": "Collision", "stat": "cold_skill_damage", "value": 10, "per": "skill_level" },
      { "source": "Asteroid", "stat": "cold_skill_damage", "value": 12.5, "per": "skill_level" },
      { "source": "Lunar Orbit", "stat": "cold_skill_damage", "value": 15, "per": "skill_level" },
      { "source": "Intelligence", "stat": "cold_skill_damage", "value": 8, "per": "attribute_point" }
    ]
  },
  {
    "id": "dark_side_of_the_moon",
    "classId": "exo",
    "name": "Dark Side of the Moon",
    "kind": "aura",
    "description": "While active, slow monsters around you. Also increases your mana replenish and energy.",
    "tags": ["Cast", "Active", "Aura"],
    "maxRank": 20,
    "requiresLevel": 8,
    "tree": "Lunar Prophet",
    "position": { "row": 1, "col": 1 },
    "ranks": [{ "rank": 1 }],
    "passiveStats": {
      "base": { "mana_replenish_pct": 5, "to_energy": 2, "slow_duration": 2 },
      "perRank": { "mana_replenish_pct": 5, "to_energy": 2 }
    }
  },
  {
    "id": "asteroid",
    "classId": "exo",
    "name": "Asteroid",
    "kind": "active",
    "description": "Cast down an asteroid from the sky dealing cold damage when landing.",
    "damageType": "cold",
    "tags": ["Cast", "Active", "Spell", "Explosion"],
    "movementDuringUse": 65,
    "range": 320,
    "baseCastRate": 1,
    "maxRank": 20,
    "requiresLevel": 8,
    "tree": "Lunar Prophet",
    "position": { "row": 1, "col": 2 },
    "ranks": [{ "rank": 1, "manaCost": 5 }],
    "damageFormula": { "base": 0.11, "perLevel": 15.89 },
    "manaCostFormula": { "base": 5, "perLevel": 1.075 },
    "bonusSources": [
      { "source": "Collision", "stat": "cold_skill_damage", "value": 10, "per": "skill_level" },
      { "source": "Tsunami", "stat": "cold_skill_damage", "value": 15, "per": "skill_level" },
      { "source": "Lunar Form", "stat": "cold_skill_damage", "value": 12.5, "per": "skill_level" },
      { "source": "Intelligence", "stat": "cold_skill_damage", "value": 7.25, "per": "attribute_point" }
    ]
  },
  {
    "id": "lunar_form",
    "classId": "exo",
    "name": "Lunar Form",
    "kind": "buff",
    "description": "Turn into a living moon and gain additional cold damage. Every time you jump, cast Collision instead.",
    "damageType": "cold",
    "tags": ["Cast", "Active", "Buff", "Shape Shift"],
    "movementDuringUse": 85,
    "baseCastRate": 1,
    "baseCooldown": 70,
    "effectDuration": 25,
    "maxRank": 20,
    "requiresLevel": 16,
    "tree": "Lunar Prophet",
    "position": { "row": 2, "col": 0 },
    "ranks": [{ "rank": 1, "manaCost": 10 }],
    "manaCostFormula": { "base": 10, "perLevel": 1.075 },
    "passiveStats": {
      "base": { "cold_skill_damage": 5.5 },
      "perRank": { "cold_skill_damage": 5.5 }
    }
  },
  {
    "id": "lunar_orbit",
    "classId": "exo",
    "name": "Lunar Orbit",
    "kind": "active",
    "description": "Unleash small moons in your orbit dealing cold damage on hit.",
    "damageType": "cold",
    "tags": ["Cast", "Active", "Spell", "Orbital"],
    "movementDuringUse": 65,
    "baseCastRate": 1,
    "maxRank": 20,
    "requiresLevel": 16,
    "tree": "Lunar Prophet",
    "position": { "row": 2, "col": 1 },
    "ranks": [{ "rank": 1, "manaCost": 5 }],
    "damageFormula": { "base": 0, "perLevel": 13 },
    "manaCostFormula": { "base": 5, "perLevel": 1.125 },
    "bonusSources": [
      { "source": "Moonlight", "stat": "cold_skill_damage", "value": 15, "per": "skill_level" },
      { "source": "Dark Side of the Moon", "stat": "cold_skill_damage", "value": 10, "per": "skill_level" },
      { "source": "Blood Moon", "stat": "cold_skill_damage", "value": 12.5, "per": "skill_level" },
      { "source": "Intelligence", "stat": "cold_skill_damage", "value": 8, "per": "attribute_point" }
    ]
  },
  {
    "id": "moonlight",
    "classId": "exo",
    "name": "Moonlight",
    "kind": "passive",
    "description": "Increases your movement speed and cold damage dealt.",
    "tags": ["Passive"],
    "maxRank": 20,
    "requiresLevel": 24,
    "tree": "Lunar Prophet",
    "position": { "row": 3, "col": 0 },
    "ranks": [{ "rank": 1 }],
    "passiveStats": {
      "base": { "movement_speed": 1, "cold_skill_damage": 3.5 },
      "perRank": { "movement_speed": 1, "cold_skill_damage": 3.5 }
    }
  },
  {
    "id": "blood_moon",
    "classId": "exo",
    "name": "Blood Moon",
    "kind": "buff",
    "description": "Turn the orbiting moons into blood moons increasing their cold damage and causing them to inflict bleeding on hit.",
    "tags": ["Cast", "Active", "Buff"],
    "movementDuringUse": 0,
    "baseCastRate": 1,
    "baseCooldown": 25,
    "effectDuration": 70,
    "maxRank": 20,
    "requiresLevel": 24,
    "tree": "Lunar Prophet",
    "position": { "row": 3, "col": 2 },
    "ranks": [{ "rank": 1, "manaCost": 5 }],
    "manaCostFormula": { "base": 5, "perLevel": 1.125 },
    "passiveStats": {
      "base": { "cold_skill_damage": 2.5, "increased_bleeding_damage": 10 },
      "perRank": { "cold_skill_damage": 2.5, "increased_bleeding_damage": 3 }
    }
  },
  {
    "id": "black_hole",
    "classId": "exo",
    "name": "Black Hole",
    "kind": "active",
    "description": "Cast a black hole on target location that slows and pulls monsters towards it dealing cold damage.",
    "damageType": "cold",
    "tags": ["Cast", "Active", "Spell", "Area of Effect"],
    "movementDuringUse": 85,
    "baseCastRate": 1,
    "baseCooldown": 4.5,
    "effectDuration": 6,
    "maxRank": 20,
    "requiresLevel": 30,
    "tree": "Lunar Prophet",
    "position": { "row": 4, "col": 1 },
    "ranks": [{ "rank": 1, "manaCost": 13 }],
    "damageFormula": { "base": 0.42, "perLevel": 15.58 },
    "manaCostFormula": { "base": 13, "perLevel": 1.125 },
    "bonusSources": [
      { "source": "Lunar Orbit", "stat": "cold_skill_damage", "value": 15, "per": "skill_level" },
      { "source": "Moonlight", "stat": "cold_skill_damage", "value": 10, "per": "skill_level" },
      { "source": "Asteroid", "stat": "cold_skill_damage", "value": 12.5, "per": "skill_level" },
      { "source": "Intelligence", "stat": "cold_skill_damage", "value": 8, "per": "attribute_point" }
    ]
  }
]
