[
  {
    "id": "fallen_gods_bloodlust",
    "name": "Fallen God's Bloodlust",
    "description": "Converts a portion of your Attack Speed into Faster Cast Rate.",
    "passiveConverts": {
      "perRank": [
        {
          "from": "increased_attack_speed",
          "to": "faster_cast_rate",
          "pct": 10
        }
      ]
    }
  },
  {
    "id": "wings_of_hatred",
    "name": "Wings of Hatred",
    "description": "Reduces landing diminish (capped at rank 1)."
  },
  {
    "id": "holy_aura",
    "name": "Holy Aura",
    "description": "Increases your and your party members attack damage and magic skill damage.",
    "passiveStats": {
      "perRank": { "attack_damage": 2, "magic_skill_damage": 2.5 }
    }
  }
]
